verilog/adder.v
module inv (
    input wire x,
    output wire y,
    input wire vdd,
    input wire gnd
);
    assign y = ~x;
endmodule
module tspc (
    input wire D,
    output reg Q,
    input wire clk,
    input wire vdd,
    input wire gnd
);
    
    always @(posedge clk) begin
        Q <= D;
    end
endmodule
module and_gate (
    input wire A,
    input wire B,
    output wire out,
    input wire vdd,
    input wire gnd
);
    assign out = (A & B);
endmodule

module or_gate (
    input wire A,
    input wire B,
    output wire out,
    input wire vdd,
    input wire gnd
);
    assign out = (A | B);
endmodule



module xor_gate (
    input wire A,
    input wire B,
    output wire out,
    input wire vdd,
    input wire gnd
);
    assign out = (A ^ B);
endmodule

module png (
    input wire A,
    input wire B,
    output wire p,
    output wire g,
    input wire vdd,
    input wire gnd
);
    wire g1;
    xor_gate xor1 (.A(A), .B(B), .out(p), .vdd(vdd), .gnd(gnd));
    and_gate and1 (.A(A), .B(B), .out(g), .vdd(vdd), .gnd(gnd));
endmodule



module clagen (
    input wire p1, p2, p3, p4,
    input wire g1, g2, g3, g4,
    input wire c1,
    output wire c2, c3, c4, c5,
    input wire vdd,
    input wire gnd
);
    assign c2 = (p1&c1) | g1;
    assign c3 = (p1&c1&p2) | p2&g1 | g2;
    assign c4 = (p1&c1&p2&p3) | p2&p3&g1 | p3&g2 | g3;
    assign c5 = (p1&c1&p2&p3&p4) | p2&p3&p4&g1 | p3&p4&g2 | p4&g3 | g4;
endmodule


module main (
    
    input wire vdd,
    input wire gnd,
    input wire [3:0] A,
    input wire [3:0] B,
    input wire c0,
    output wire [4:0] s
    // output wire c4
);
    wire [3:0] p, g;
    wire c1, c2, c3;

    png x1 (.A(A[0]), .B(B[0]), .p(p[0]), .g(g[0]), .vdd(vdd), .gnd(gnd));
    png x2 (.A(A[1]), .B(B[1]), .p(p[1]), .g(g[1]), .vdd(vdd), .gnd(gnd));
    png x3 (.A(A[2]), .B(B[2]), .p(p[2]), .g(g[2]), .vdd(vdd), .gnd(gnd));
    png x4 (.A(A[3]), .B(B[3]), .p(p[3]), .g(g[3]), .vdd(vdd), .gnd(gnd));

    clagen x5 (
        .p1(p[0]), .p2(p[1]), .p3(p[2]), .p4(p[3]),
        .g1(g[0]), .g2(g[1]), .g3(g[2]), .g4(g[3]),
        .c1(c0), .c2(c1), .c3(c2), .c4(c3), .c5(s[4]),
        .vdd(vdd), .gnd(gnd)
    );

    assign s[0] = p[0] ^ c0;
    assign s[1] = p[1] ^ c1;
    assign s[2] = p[2] ^ c2;
    assign s[3] = p[3] ^ c3;

endmodule

module adder(
    input wire [3:0] A,
    input wire [3:0] B,
    input wire clk,
    output wire [4:0] S,
    // output wire C4,
    input wire vdd,
    input wire gnd,
    input wire c0

);
    wire [3:0]  A1, B1;
    wire [4:0]  S1;
    // wire c41;
    tspc x1 (.D(A[0]), .Q(A1[0]), .clk(clk), .vdd(vdd), .gnd(gnd));
    tspc x2 (.D(A[1]), .Q(A1[1]), .clk(clk), .vdd(vdd), .gnd(gnd));
    tspc x3 (.D(A[2]), .Q(A1[2]), .clk(clk), .vdd(vdd), .gnd(gnd));
    tspc x4 (.D(A[3]), .Q(A1[3]), .clk(clk), .vdd(vdd), .gnd(gnd));
    tspc x5 (.D(B[0]), .Q(B1[0]), .clk(clk), .vdd(vdd), .gnd(gnd));
    tspc x6 (.D(B[1]), .Q(B1[1]), .clk(clk), .vdd(vdd), .gnd(gnd));
    tspc x7 (.D(B[2]), .Q(B1[2]), .clk(clk), .vdd(vdd), .gnd(gnd));
    tspc x8 (.D(B[3]), .Q(B1[3]), .clk(clk), .vdd(vdd), .gnd(gnd));
    main x9 (.A(A1), .B(B1), .c0(c0), .s(S1), .vdd(vdd), .gnd(gnd));
    tspc x10 (.D(S1[0]), .Q(S[0]), .clk(clk), .vdd(vdd), .gnd(gnd));
    tspc x11 (.D(S1[1]), .Q(S[1]), .clk(clk), .vdd(vdd), .gnd(gnd));
    tspc x12 (.D(S1[2]), .Q(S[2]), .clk(clk), .vdd(vdd), .gnd(gnd));
    tspc x13 (.D(S1[3]), .Q(S[3]), .clk(clk), .vdd(vdd), .gnd(gnd));
    tspc x14 (.D(S1[4]), .Q(S[4]), .clk(clk), .vdd(vdd), .gnd(gnd));
    
endmodule

verilog/adder_tb.v
`timescale 1ns / 1ps


module tb_circuit;

    reg clk, vdd, gnd;
    reg [3:0] A, B;
    wire [4:0] g;
    wire c4;
    reg c0;

    adder uut (
        .A(A),
        .B(B),
        .clk(clk),
        .S(g),
        // .C4(c4),
        .c0(c0),
        .vdd(vdd),
        .gnd(gnd)
    );
    always #5 clk = ~clk;

    initial begin
        clk = 0;
        

        A = 4'b0001; B = 4'b0010; c0=1'b1; #20;  
        $display("A=%b B=%b S=%b ", A, B,g);
        A = 4'b1111; B = 4'b0001; c0=1'b0; #20;  
        $display("A=%b B=%b S=%b ", A, B,g);
        A = 4'b1010; B = 4'b0100; c0=1'b1; #20; 
        $display("A=%b B=%b S=%b ", A, B,g);

        $finish;
    end
    initial begin
    $dumpfile("cla_adder");
    $dumpvars(0,tb_circuit);
end

endmodule

verilog/cla_adder.vcd
$date
	Mon Nov 18 22:30:24 2024
$end
$version
	Icarus Verilog
$end
$timescale
	1ps
$end
$scope module tb_circuit $end
$var wire 5 ! g [4:0] $end
$var reg 4 " A [3:0] $end
$var reg 4 # B [3:0] $end
$var reg 1 $ c0 $end
$var reg 1 % clk $end
$var reg 1 & gnd $end
$var reg 1 ' vdd $end
$scope module uut $end
$var wire 4 ( A [3:0] $end
$var wire 4 ) B [3:0] $end
$var wire 1 $ c0 $end
$var wire 1 % clk $end
$var wire 1 & gnd $end
$var wire 1 ' vdd $end
$var wire 5 * S1 [4:0] $end
$var wire 5 + S [4:0] $end
$var wire 4 , B1 [3:0] $end
$var wire 4 - A1 [3:0] $end
$scope module x1 $end
$var wire 1 . D $end
$var wire 1 % clk $end
$var wire 1 & gnd $end
$var wire 1 ' vdd $end
$var reg 1 / Q $end
$upscope $end
$scope module x10 $end
$var wire 1 0 D $end
$var wire 1 % clk $end
$var wire 1 & gnd $end
$var wire 1 ' vdd $end
$var reg 1 1 Q $end
$upscope $end
$scope module x11 $end
$var wire 1 2 D $end
$var wire 1 % clk $end
$var wire 1 & gnd $end
$var wire 1 ' vdd $end
$var reg 1 3 Q $end
$upscope $end
$scope module x12 $end
$var wire 1 4 D $end
$var wire 1 % clk $end
$var wire 1 & gnd $end
$var wire 1 ' vdd $end
$var reg 1 5 Q $end
$upscope $end
$scope module x13 $end
$var wire 1 6 D $end
$var wire 1 % clk $end
$var wire 1 & gnd $end
$var wire 1 ' vdd $end
$var reg 1 7 Q $end
$upscope $end
$scope module x14 $end
$var wire 1 8 D $end
$var wire 1 % clk $end
$var wire 1 & gnd $end
$var wire 1 ' vdd $end
$var reg 1 9 Q $end
$upscope $end
$scope module x2 $end
$var wire 1 : D $end
$var wire 1 % clk $end
$var wire 1 & gnd $end
$var wire 1 ' vdd $end
$var reg 1 ; Q $end
$upscope $end
$scope module x3 $end
$var wire 1 < D $end
$var wire 1 % clk $end
$var wire 1 & gnd $end
$var wire 1 ' vdd $end
$var reg 1 = Q $end
$upscope $end
$scope module x4 $end
$var wire 1 > D $end
$var wire 1 % clk $end
$var wire 1 & gnd $end
$var wire 1 ' vdd $end
$var reg 1 ? Q $end
$upscope $end
$scope module x5 $end
$var wire 1 @ D $end
$var wire 1 % clk $end
$var wire 1 & gnd $end
$var wire 1 ' vdd $end
$var reg 1 A Q $end
$upscope $end
$scope module x6 $end
$var wire 1 B D $end
$var wire 1 % clk $end
$var wire 1 & gnd $end
$var wire 1 ' vdd $end
$var reg 1 C Q $end
$upscope $end
$scope module x7 $end
$var wire 1 D D $end
$var wire 1 % clk $end
$var wire 1 & gnd $end
$var wire 1 ' vdd $end
$var reg 1 E Q $end
$upscope $end
$scope module x8 $end
$var wire 1 F D $end
$var wire 1 % clk $end
$var wire 1 & gnd $end
$var wire 1 ' vdd $end
$var reg 1 G Q $end
$upscope $end
$scope module x9 $end
$var wire 4 H A [3:0] $end
$var wire 4 I B [3:0] $end
$var wire 1 $ c0 $end
$var wire 1 & gnd $end
$var wire 1 ' vdd $end
$var wire 5 J s [4:0] $end
$var wire 4 K p [3:0] $end
$var wire 4 L g [3:0] $end
$var wire 1 M c3 $end
$var wire 1 N c2 $end
$var wire 1 O c1 $end
$scope module x1 $end
$var wire 1 P A $end
$var wire 1 Q B $end
$var wire 1 & gnd $end
$var wire 1 ' vdd $end
$var wire 1 R p $end
$var wire 1 S g $end
$scope module and1 $end
$var wire 1 P A $end
$var wire 1 Q B $end
$var wire 1 & gnd $end
$var wire 1 S out $end
$var wire 1 ' vdd $end
$upscope $end
$scope module xor1 $end
$var wire 1 P A $end
$var wire 1 Q B $end
$var wire 1 & gnd $end
$var wire 1 R out $end
$var wire 1 ' vdd $end
$upscope $end
$upscope $end
$scope module x2 $end
$var wire 1 T A $end
$var wire 1 U B $end
$var wire 1 & gnd $end
$var wire 1 ' vdd $end
$var wire 1 V p $end
$var wire 1 W g $end
$scope module and1 $end
$var wire 1 T A $end
$var wire 1 U B $end
$var wire 1 & gnd $end
$var wire 1 W out $end
$var wire 1 ' vdd $end
$upscope $end
$scope module xor1 $end
$var wire 1 T A $end
$var wire 1 U B $end
$var wire 1 & gnd $end
$var wire 1 V out $end
$var wire 1 ' vdd $end
$upscope $end
$upscope $end
$scope module x3 $end
$var wire 1 X A $end
$var wire 1 Y B $end
$var wire 1 & gnd $end
$var wire 1 ' vdd $end
$var wire 1 Z p $end
$var wire 1 [ g $end
$scope module and1 $end
$var wire 1 X A $end
$var wire 1 Y B $end
$var wire 1 & gnd $end
$var wire 1 [ out $end
$var wire 1 ' vdd $end
$upscope $end
$scope module xor1 $end
$var wire 1 X A $end
$var wire 1 Y B $end
$var wire 1 & gnd $end
$var wire 1 Z out $end
$var wire 1 ' vdd $end
$upscope $end
$upscope $end
$scope module x4 $end
$var wire 1 \ A $end
$var wire 1 ] B $end
$var wire 1 & gnd $end
$var wire 1 ' vdd $end
$var wire 1 ^ p $end
$var wire 1 _ g $end
$scope module and1 $end
$var wire 1 \ A $end
$var wire 1 ] B $end
$var wire 1 & gnd $end
$var wire 1 _ out $end
$var wire 1 ' vdd $end
$upscope $end
$scope module xor1 $end
$var wire 1 \ A $end
$var wire 1 ] B $end
$var wire 1 & gnd $end
$var wire 1 ^ out $end
$var wire 1 ' vdd $end
$upscope $end
$upscope $end
$scope module x5 $end
$var wire 1 $ c1 $end
$var wire 1 O c2 $end
$var wire 1 N c3 $end
$var wire 1 M c4 $end
$var wire 1 ` c5 $end
$var wire 1 a g1 $end
$var wire 1 b g2 $end
$var wire 1 c g3 $end
$var wire 1 d g4 $end
$var wire 1 & gnd $end
$var wire 1 e p1 $end
$var wire 1 f p2 $end
$var wire 1 g p3 $end
$var wire 1 h p4 $end
$var wire 1 ' vdd $end
$upscope $end
$upscope $end
$upscope $end
$upscope $end
$enddefinitions $end
#0
$dumpvars
xh
xg
xf
xe
xd
xc
xb
xa
x`
x_
x^
x]
x\
x[
xZ
xY
xX
xW
xV
xU
xT
xS
xR
xQ
xP
xO
xN
xM
bx L
bx K
bx J
bx I
bx H
xG
0F
xE
0D
xC
1B
xA
0@
x?
0>
x=
0<
x;
0:
x9
x8
x7
x6
x5
x4
x3
x2
x1
x0
x/
1.
bx -
bx ,
bx +
bx *
b10 )
b1 (
x'
x&
0%
1$
b10 #
b1 "
bx !
$end
#5000
14
06
08
1N
0`
0M
02
00
1O
b100 *
b100 J
0a
1e
0b
1f
0c
0g
0d
0h
0S
1R
0W
1V
0[
0Z
b0 L
0_
b11 K
0^
1P
0T
0X
0\
0Q
1U
0Y
0]
1/
0;
0=
b1 -
b1 H
0?
0A
1C
0E
b10 ,
b10 I
0G
1%
#10000
0%
#15000
09
07
15
03
b100 !
b100 +
01
1%
#20000
04
12
0N
10
0O
b11 *
b11 J
1@
0B
1:
1<
1>
0%
0$
b1 #
b1 )
b1111 "
b1111 (
#25000
18
1`
1M
02
1N
04
06
00
1O
b10000 *
b10000 J
1g
1h
1a
0e
1Z
1^
b1 L
1S
b1110 K
0R
1T
1X
1\
1Q
0U
1;
1=
b1111 -
b1111 H
1?
1A
b1 ,
b1 I
0C
11
13
b11 !
b11 +
05
1%
#30000
0%
#35000
19
03
b10000 !
b10000 +
01
1%
#40000
10
b10001 *
b10001 J
0@
1D
0.
0<
0%
1$
b100 #
b100 )
b1010 "
b1010 (
#45000
16
08
14
0`
0M
12
0N
b1111 *
b1111 J
0O
0a
b0 L
0S
0P
0X
0Q
1Y
0/
b1010 -
b1010 H
0=
0A
b100 ,
b100 I
1E
b10001 !
b10001 +
11
1%
#50000
0%
#55000
09
17
15
b1111 !
b1111 +
13
1%
